QtTables/CellWidgets.py
QtTables/Creators.py
QtTables/TableWidget.py
QtTables/Validators.py
QtTables/__init__.py
QtTables-0.9.5.dist-info/METADATA
QtTables-0.9.5.dist-info/WHEEL
QtTables-0.9.5.dist-info/top_level.txt
QtTables-0.9.5.dist-info/RECORD
