Metadata-Version: 2.1
Name: QtTables
Version: 0.9.5
Summary: Easy way to create tables in PySide2.
Author: Savvin Anton
Author-email: anv.savvin@gmail.com
License: GPL-3.0 license
Keywords: python
Platform: Windows
Platform: Unix
Classifier: Programming Language :: Python :: 3
